Metadata-Version: 2.1
Name: netbox2ypconfig
Version: 1.0.2.2
Summary: Program to construct ypconfig YAML configuration file from NetBox.
Home-page: https://vcs.cyberfusion.nl/open-source/netbox2ypconfig
Author: William Edwards
Author-email: opensource@cyberfusion.nl
License: MIT
Keywords: cyberfusion,ypconfig
Platform: linux
Classifier: Programming Language :: Python :: 3
Classifier: License :: OSI Approved :: MIT License
Classifier: Operating System :: OS Independent
Requires-Python: >=3.6
License-File: LICENSE
